tlstofu.py
tls-tofu/__init__.py
tls-tofu/tlstofu.py
tls_tofu/__init__.py
tls_tofu/tlstofu.py
tls_tofu-1.0.0.dist-info/METADATA
tls_tofu-1.0.0.dist-info/WHEEL
tls_tofu-1.0.0.dist-info/top_level.txt
tls_tofu-1.0.0.dist-info/RECORD
