Metadata-Version: 2.1
Name: tls-tofu
Version: 1.0.0
Summary: A package implementing TOFU with TLS
Home-page: https://github.com/faelif/tls-tofu
Author: Felicity Grey
Author-email: bloopy813@gmail.com
License: UNKNOWN
Project-URL: Bug Tracker, https://github.com/faelif/tls-tofu/issues
Platform: UNKNOWN
Classifier: Programming Language :: Python :: 3
Classifier: License :: OSI Approved :: MIT License
Classifier: Operating System :: OS Independent
Requires-Python: >=3.6
